kleides_mfa/__init__.py
kleides_mfa/admin.py
kleides_mfa/apps.py
kleides_mfa/conf.py
kleides_mfa/decorators.py
kleides_mfa/forms.py
kleides_mfa/middleware.py
kleides_mfa/registry.py
kleides_mfa/signals.py
kleides_mfa/urls.py
kleides_mfa/static/js/kleides_mfa/jquery.qrcode.min.js
kleides_mfa/static/js/kleides_mfa/recovery-code.js
kleides_mfa/templates/kleides_mfa/base.html
kleides_mfa/templates/kleides_mfa/device_confirm_delete.html
kleides_mfa/templates/kleides_mfa/device_create_form.html
kleides_mfa/templates/kleides_mfa/device_form.html
kleides_mfa/templates/kleides_mfa/device_list.html
kleides_mfa/templates/kleides_mfa/device_recovery-code_list.html
kleides_mfa/templates/kleides_mfa/device_totp_create_form.html
kleides_mfa/templates/kleides_mfa/device_verify_form.html
kleides_mfa/templates/kleides_mfa/form.html
kleides_mfa/templates/kleides_mfa/login.html
kleides_mfa/templates/kleides_mfa/plugin_list.html
kleides_mfa/views/__init__.py
kleides_mfa/views/auth.py
kleides_mfa/views/devices.py
kleides_mfa/views/mixins.py
kleides_mfa-0.2.4.dist-info/AUTHORS.rst
kleides_mfa-0.2.4.dist-info/LICENSE
kleides_mfa-0.2.4.dist-info/METADATA
kleides_mfa-0.2.4.dist-info/WHEEL
kleides_mfa-0.2.4.dist-info/top_level.txt
kleides_mfa-0.2.4.dist-info/RECORD
