Metadata-Version: 2.1
Name: kleides-mfa
Version: 0.2.4
Summary: Interface components to configure and manage multi factor authentication
Home-page: https://github.com/ossobv/kleides-mfa
Author: Harm Geerts
Author-email: hgeerts@osso.nl
License: GNU General Public License v3
Keywords: kleides django-otp two factor authentication 2fa
Classifier: Development Status :: 4 - Beta
Classifier: Intended Audience :: Developers
Classifier: License :: OSI Approved :: GNU General Public License v3 (GPLv3)
Classifier: Environment :: Web Environment
Classifier: Natural Language :: English
Classifier: Framework :: Django
Classifier: Framework :: Django :: 3.2
Classifier: Framework :: Django :: 4.2
Classifier: Framework :: Django :: 5.0
Classifier: Programming Language :: Python
Classifier: Programming Language :: Python :: 3
Classifier: Programming Language :: Python :: 3.8
Classifier: Programming Language :: Python :: 3.9
Classifier: Programming Language :: Python :: 3.10
Classifier: Programming Language :: Python :: 3.11
Classifier: Programming Language :: Python :: 3.12
Classifier: Topic :: System :: Systems Administration :: Authentication/Directory
Requires-Python: >=3.6
License-File: LICENSE
License-File: AUTHORS.rst
Requires-Dist: django-otp >=0.7.0
Provides-Extra: docs
Requires-Dist: django-otp-yubikey ; extra == 'docs'
Requires-Dist: readthedocs-sphinx-search ==0.1.0 ; extra == 'docs'
Requires-Dist: Sphinx ==4.0.3 ; extra == 'docs'
Requires-Dist: sphinx-rtd-theme ==0.5.2 ; extra == 'docs'
Provides-Extra: test
Requires-Dist: coverage ; extra == 'test'
Requires-Dist: django-otp-yubikey ; extra == 'test'
Requires-Dist: factory-boy ; extra == 'test'
Requires-Dist: pytest ; extra == 'test'
Requires-Dist: pytest-cov ; extra == 'test'
Requires-Dist: pytest-django ; extra == 'test'
